examples/__init__.py
examples/change_batch_yjs.py
examples/change_formatting_yjs.py
examples/create_sheet_yjs.py
examples/create_table_yjs.py
examples/delete_column_yjs.py
examples/delete_row_yjs.py
examples/delete_table_column_yjs.py
examples/immer_workflow.py
examples/insert_column_yjs.py
examples/insert_row_yjs.py
examples/insert_table_column_yjs.py
examples/update_sheet_yjs.py
examples/update_table_yjs.py
examples/yjs_integration.py
examples/yjs_websocket_client.py
rowsncolumns_spreadsheet/__init__.py
rowsncolumns_spreadsheet/cell_xfs.py
rowsncolumns_spreadsheet/dag.py
rowsncolumns_spreadsheet/datatype.py
rowsncolumns_spreadsheet/efficient_interface.py
rowsncolumns_spreadsheet/efficient_patches.py
rowsncolumns_spreadsheet/immer_interface.py
rowsncolumns_spreadsheet/immer_like_patches.py
rowsncolumns_spreadsheet/interface.py
rowsncolumns_spreadsheet/operations.py
rowsncolumns_spreadsheet/patches.py
rowsncolumns_spreadsheet/sheet_cell.py
rowsncolumns_spreadsheet/sheet_cell_helpers.py
rowsncolumns_spreadsheet/spreadsheet.py
rowsncolumns_spreadsheet/types.py
rowsncolumns_spreadsheet/utils.py
rowsncolumns_spreadsheet/interface/__init__.py
rowsncolumns_spreadsheet/interface/apply_fill.py
rowsncolumns_spreadsheet/interface/fill.py
rowsncolumns_spreadsheet/yjs/__init__.py
rowsncolumns_spreadsheet/yjs/change_batch.py
rowsncolumns_spreadsheet/yjs/change_formatting.py
rowsncolumns_spreadsheet/yjs/create_new_sheet.py
rowsncolumns_spreadsheet/yjs/create_table.py
rowsncolumns_spreadsheet/yjs/delete_column.py
rowsncolumns_spreadsheet/yjs/delete_row.py
rowsncolumns_spreadsheet/yjs/delete_table_column.py
rowsncolumns_spreadsheet/yjs/insert_column.py
rowsncolumns_spreadsheet/yjs/insert_row.py
rowsncolumns_spreadsheet/yjs/insert_table_column.py
rowsncolumns_spreadsheet/yjs/managers.py
rowsncolumns_spreadsheet/yjs/models.py
rowsncolumns_spreadsheet/yjs/sheet_utils.py
rowsncolumns_spreadsheet/yjs/update_sheet.py
rowsncolumns_spreadsheet/yjs/update_table.py
tests/__init__.py
rowsncolumns_spreadsheet-0.1.9.dist-info/METADATA
rowsncolumns_spreadsheet-0.1.9.dist-info/WHEEL
rowsncolumns_spreadsheet-0.1.9.dist-info/top_level.txt
rowsncolumns_spreadsheet-0.1.9.dist-info/RECORD
