Metadata-Version: 2.4
Name: rowsncolumns-spreadsheet
Version: 0.1.9
Summary: Python implementation of rowsncolumns spreadsheet operations
Author: Rows & Columns
License: MIT
Requires-Python: >=3.8
Requires-Dist: pydantic>=2.0.0
Requires-Dist: typing-extensions>=4.0.0
Requires-Dist: jsonpatch>=1.33
Requires-Dist: networkx>=3.1
Requires-Dist: openpyxl>=3.1.0
Provides-Extra: dev
Requires-Dist: pytest>=7.0.0; extra == "dev"
Requires-Dist: pytest-cov>=4.0.0; extra == "dev"
Requires-Dist: black>=23.0.0; extra == "dev"
Requires-Dist: mypy>=1.0.0; extra == "dev"
Dynamic: author
Dynamic: requires-python
